setup.py
django_oscar_fees/__init__.py
django_oscar_fees/admin.py
django_oscar_fees/applicator.py
django_oscar_fees/conditions.py
django_oscar_fees/config.py
django_oscar_fees/exceptions.py
django_oscar_fees/fees.py
django_oscar_fees/managers.py
django_oscar_fees/middleware.py
django_oscar_fees/mixins.py
django_oscar_fees/models.py
django_oscar_fees/results.py
django_oscar_fees/signals.py
django_oscar_fees.egg-info/PKG-INFO
django_oscar_fees.egg-info/SOURCES.txt
django_oscar_fees.egg-info/dependency_links.txt
django_oscar_fees.egg-info/pbr.json
django_oscar_fees.egg-info/top_level.txt
django_oscar_fees/migrations/0001_initial.py
django_oscar_fees/migrations/0002_auto_20170811_1403.py
django_oscar_fees/migrations/__init__.py