Metadata-Version: 1.1
Name: django-oscar-fees
Version: 0.2
Summary: Apply fees to baskets and orders in django-oscar
Home-page: https://github.com/JorrandeWit/django-oscar-fees
Author: Jorran de Wit
Author-email: jorrandewit@outlook.com
License: BSD
Keywords: ecommerce,oscar
Platform: UNKNOWN
Classifier: Development Status :: 4 - Beta
Classifier: Environment :: Web Environment
Classifier: Framework :: Django :: 1.9
Classifier: Framework :: Django :: 1.10
Classifier: Framework :: Django :: 1.11
Classifier: Intended Audience :: Developers
Classifier: License :: OSI Approved :: BSD License
Classifier: Operating System :: OS Independent
Classifier: Programming Language :: Python :: 3
Classifier: Programming Language :: Python :: 3.2
Classifier: Programming Language :: Python :: 3.3
Classifier: Programming Language :: Python :: 3.4
Classifier: Programming Language :: Python :: 3.5
Classifier: Programming Language :: Python :: 3.6
